setup.py
cloudflare_v4/__init__.py
cloudflare_v4/exceptions.py
cloudflare_v4/logger.py
python_cloudflare_v4.egg-info/PKG-INFO
python_cloudflare_v4.egg-info/SOURCES.txt
python_cloudflare_v4.egg-info/dependency_links.txt
python_cloudflare_v4.egg-info/top_level.txt