Metadata-Version: 1.0
Name: python-cloudflare-v4
Version: 1.0
Summary: Python wrapper for the CloudFlare v4 API
Home-page: http://github.com/python-cloudflare/python-cloudflare-v4
Author: gnowxilef
Author-email: felix@fawong.com
License: UNKNOWN
Platform: UNKNOWN
